apimatic_requests_client_adapter/__init__.py
apimatic_requests_client_adapter/requests_client.py
apimatic_requests_client_adapter-0.1.8.dist-info/licenses/LICENSE
tests/__init__.py
tests/apimatic_requests_client_adapter/__init__.py
tests/apimatic_requests_client_adapter/base.py
tests/apimatic_requests_client_adapter/models/__init__.py
tests/apimatic_requests_client_adapter/models/external/__init__.py
tests/apimatic_requests_client_adapter/models/external/http_response.py
tests/apimatic_requests_client_adapter/models/internal/__init__.py
tests/apimatic_requests_client_adapter/models/internal/http_request.py
tests/apimatic_requests_client_adapter/models/internal/http_response.py
tests/apimatic_requests_client_adapter/models/internal/http_response_factory.py
tests/apimatic_requests_client_adapter/requests_client_tests/__init__.py
tests/apimatic_requests_client_adapter/requests_client_tests/test_requests_client.py
apimatic_requests_client_adapter-0.1.8.dist-info/METADATA
apimatic_requests_client_adapter-0.1.8.dist-info/WHEEL
apimatic_requests_client_adapter-0.1.8.dist-info/top_level.txt
apimatic_requests_client_adapter-0.1.8.dist-info/RECORD
