Metadata-Version: 2.4
Name: apimatic-requests-client-adapter
Version: 0.1.8
Summary: An adapter for requests client library consumed by the SDKs generated with APIMatic
Home-page: https://github.com/apimatic/requests-client-adapter
Author: APIMatic
Author-email: support@apimatic.io
License: MIT
License-File: LICENSE
Requires-Dist: apimatic-core-interfaces~=0.1.0
Requires-Dist: requests~=2.31
Requires-Dist: cachecontrol~=0.12.6
Dynamic: author
Dynamic: author-email
Dynamic: description
Dynamic: description-content-type
Dynamic: home-page
Dynamic: license
Dynamic: license-file
Dynamic: requires-dist
Dynamic: summary
